pycbf/__init__.py
pycbf/_pycbf.cpython-39-i386-linux-gnu.so
pycbf/_wrapper.py
pycbf/img.c
pycbf/img.cpython-39-i386-linux-gnu.so
pycbf/img.pxd
pycbf/img.pyi
pycbf/img.pyx
pycbf/py.typed
pycbf/utils.py
pycbf-0.9.6.7.dist-info/METADATA
pycbf-0.9.6.7.dist-info/WHEEL
pycbf-0.9.6.7.dist-info/top_level.txt
pycbf-0.9.6.7.dist-info/RECORD
pycbf-0.9.6.7.dist-info/licenses/LICENCE.txt
