Metadata-Version: 2.4
Name: pycbf
Version: 0.9.6.7
Summary: An API for CBF/imgCIF Crystallographic Binary Files
Author: Paul J. Ellis
Author-email: "Herbert J. Bernstein" <yaya@bernstein-plus-sons.com>
Maintainer-email: Nicholas Devenish <ndevenish@gmail.com>
License-Expression: LGPL-2.1-or-later
Project-URL: Homepate, http://www.bernstein-plus-sons.com/software/CBF/
Project-URL: Repository, https://github.com/dials/pycbf
Requires-Python: >=3.9
License-File: LICENCE.txt
Requires-Dist: numpy>=1.26; python_version <= "3.12"
Requires-Dist: numpy>=2.1; python_version >= "3.13"
Dynamic: license-file
